[
  {
    "title": "How charitable contributions affect Americans’ taxes",
    "description": "PolicyEngine estimates the tax impact of your donations for free.",
    "date": "2022-11-29",
    "tags": ["global"],
    "filename": "charitable-contributions.md",
    "image": "charitable-contributions.png",
    "authors": ["max-ghenis"]
  },
  {
    "title": "Maryland's standard deduction",
    "description": "PolicyEngine computes the program’s impact on Maryland and individual households.",
    "date": "2022-11-22",
    "tags": ["us"],
    "filename": "maryland-standard-deduction.md",
    "image": "maryland-standard-deduction.png",
    "authors": ["kevin-foster"]
  }
]
